podhub.meh-0.1.12-py3.4-nspkg.pth
podhub/meh/__init__.py
podhub/meh/util.py
podhub.meh-0.1.12.dist-info/DESCRIPTION.rst
podhub.meh-0.1.12.dist-info/METADATA
podhub.meh-0.1.12.dist-info/metadata.json
podhub.meh-0.1.12.dist-info/namespace_packages.txt
podhub.meh-0.1.12.dist-info/RECORD
podhub.meh-0.1.12.dist-info/top_level.txt
podhub.meh-0.1.12.dist-info/WHEEL
