Metadata-Version: 2.0
Name: podhub.meh
Version: 0.1.12
Summary: Flask framework with defaults.
Home-page: https://github.com/podhub/meh
Author: Jon Chen
Author-email: bsd@voltaire.sh
License: BSD 3-Clause License
Platform: UNKNOWN
Classifier: Intended Audience :: Developers
Classifier: License :: OSI Approved :: Apache Software License
Classifier: Operating System :: POSIX :: Linux
Classifier: Programming Language :: Python
Classifier: Programming Language :: Python :: 3
Classifier: Programming Language :: Python :: 3.2
Classifier: Programming Language :: Python :: 3.3
Classifier: Programming Language :: Python :: 3.4
Requires-Dist: Flask (==0.10.1)
